wappy/__init__.py
wappy/main.py
wappy/md5.py
wappy/technologies.json
wappy/update.py
wappy-0.0.1.dist-info/LICENSE
wappy-0.0.1.dist-info/METADATA
wappy-0.0.1.dist-info/WHEEL
wappy-0.0.1.dist-info/entry_points.txt
wappy-0.0.1.dist-info/top_level.txt
wappy-0.0.1.dist-info/RECORD
