Metadata-Version: 2.1
Name: wappy
Version: 0.0.1
Summary: Discover web technologies in web applications from your terminal
Home-page: https://github.com/blackarrowsec/wappy
Author: Eloy Perez
Author-email: eloy.perez@tarlogic.com
License: UNKNOWN
Project-URL: Repository, https://github.com/blackarrowsec/wappy
Platform: UNKNOWN
Classifier: Programming Language :: Python :: 3
Classifier: License :: OSI Approved :: GNU General Public License v3 (GPLv3)
Requires-Dist: requests
Requires-Dist: wap
